<core:FragmentDefinition xmlns:core="sap.ui.core" xmlns="sap.m" xmlns:form="sap.ui.layout.form" controllerName="pwc.portal.eval.ClubEvaluations.view.Applications.WebsiteQuality.controller.Dialog9">
    <Dialog horizontalScrolling="true" showHeader="true" state="None" stretch="false" title="{WebsiteQualityi18n>Editwebsiteinfo}" type="Standard" verticalScrolling="true" content="{/ClubBasicInfo2}">
        <content>
            <form:Form xmlns:cd="http://schemas.sap.com/sapui5/extension/sap.ui.core.CustomData/1" width="100%" editable="true" visible="true">
                <form:title/>
                <form:formContainers>
                    <form:FormContainer visible="true">
                        <form:formElements>
                            <form:FormElement visible="true">
                                <form:label>
                                    <Label text="{WebsiteQualityi18n>WebsiteLink}" design="Standard" width="100%" required="false" textAlign="Begin" textDirection="Inherit" visible="true"/>
                                </form:label>
                                <form:fields>
                                    <Input type="Text" showValueHelp="false" enabled="true" visible="true" width="auto" valueHelpOnly="false" required="true" valueStateText="Invalid entry" maxLength="0" value="{website_link}" id="website_link"/>
                                </form:fields>
                            </form:FormElement>
                            <form:FormElement visible="true">
                                <form:label>
                                    <Label text="{WebsiteQualityi18n>WebsiteDescription}" design="Standard" width="100%" required="false" textAlign="Begin" textDirection="Inherit" visible="true"/>
                                </form:label>
                                <form:fields>
                                    <TextArea rows="2" cols="20" maxLength="0" wrapping="None" enabled="true" required="true" valueStateText="Invalid entry" visible="true" value="{website_description}" id="website_description"/>
                                </form:fields> 
                            </form:FormElement>
                        </form:formElements>
                        <form:title/>
                    </form:FormContainer>
                </form:formContainers>
                <form:layout>
                    <form:ResponsiveGridLayout adjustLabelSpan="false" columnsL="2" labelSpanL="3" columnsM="1" labelSpanM="2" labelSpanS="12"/>
                </form:layout>
            </form:Form>
        </content>
        <beginButton/>
        <buttons>
            <Button text="{WebsiteQualityi18n>OK}" type="Default" iconFirst="true" width="auto" enabled="true" visible="true" iconDensityAware="false" press="_onButtonPress"/>
            <Button text="{WebsiteQualityi18n>Cancel}" type="Default" iconFirst="true" width="auto" enabled="true" visible="true" iconDensityAware="false" press="_onButtonPress1"/>
        </buttons>
        <customHeader/>
        <endButton/>
        <subHeader/>
    </Dialog>
</core:FragmentDefinition>